Rosehip/__init__.py
Rosehip/image.jpg
Rosehip/apps/programming/README.md
Rosehip/apps/programming/bat/__init__.py
Rosehip/apps/programming/c#/__init__.py
Rosehip/apps/programming/html/__init__.py
Rosehip/apps/programming/javascript/__init__.py
Rosehip/apps/programming/powershell/__init__.py
Rosehip/apps/programming/python/__init__.py
Rosehip/apps/programming/visual basic script/__init__.py
Rosehip/apps/tools/background color/__init__.py
Rosehip/apps/tools/background image/__init__.py
Rosehip/apps/tools/calculator/__init__.py
Rosehip/apps/tools/clock/__init__.py
Rosehip/apps/tools/music/__init__.py
Rosehip/apps/tools/shut down/__init__.py
Rosehip/apps/tools/video/README.md
Rosehip/apps/tools/video/__init__.py
Rosehip/apps/tools/video/video.mp4
Rosehip/apps/util/animation/__init__.py
Rosehip/apps/util/animation/frames/README.md
Rosehip/apps/util/animation/frames/frame-0.png
Rosehip/apps/util/animation/frames/frame-1.png
Rosehip/apps/util/animation/frames/frame-10.png
Rosehip/apps/util/animation/frames/frame-11.png
Rosehip/apps/util/animation/frames/frame-12.png
Rosehip/apps/util/animation/frames/frame-13.png
Rosehip/apps/util/animation/frames/frame-14.png
Rosehip/apps/util/animation/frames/frame-15.png
Rosehip/apps/util/animation/frames/frame-16.png
Rosehip/apps/util/animation/frames/frame-17.png
Rosehip/apps/util/animation/frames/frame-18.png
Rosehip/apps/util/animation/frames/frame-19.png
Rosehip/apps/util/animation/frames/frame-2.png
Rosehip/apps/util/animation/frames/frame-20.png
Rosehip/apps/util/animation/frames/frame-3.png
Rosehip/apps/util/animation/frames/frame-4.png
Rosehip/apps/util/animation/frames/frame-5.png
Rosehip/apps/util/animation/frames/frame-6.png
Rosehip/apps/util/animation/frames/frame-7.png
Rosehip/apps/util/animation/frames/frame-8.png
Rosehip/apps/util/animation/frames/frame-9.png
Rosehip/apps/util/camera/__init__.py
Rosehip/apps/util/chrome/README.md
Rosehip/apps/util/chrome/__init__.py
Rosehip/apps/util/kill-cam/README.md
rosehip-1.1.0.dist-info/LICENSE
rosehip-1.1.0.dist-info/METADATA
rosehip-1.1.0.dist-info/WHEEL
rosehip-1.1.0.dist-info/entry_points.txt
rosehip-1.1.0.dist-info/top_level.txt
rosehip-1.1.0.dist-info/RECORD
