Metadata-Version: 2.1
Name: rosehip
Version: 1.1.0
Summary: Reliable Operating System by Elisha Hollander Implemented Python
Home-page: https://github.com/donno2048/Rosehip-pypi
Author: Elisha Hollander
License: MIT
Platform: UNKNOWN
Classifier: Operating System :: Microsoft :: Windows
Classifier: License :: OSI Approved :: MIT License
Classifier: Programming Language :: Python :: 3
License-File: LICENSE
Requires-Dist: roin
